homepluscontrol/__init__.py
homepluscontrol/authentication.py
homepluscontrol/homeplusapi.py
homepluscontrol/homeplusautomation.py
homepluscontrol/homeplusinteractivemodule.py
homepluscontrol/homepluslight.py
homepluscontrol/homeplusmodule.py
homepluscontrol/homeplusplant.py
homepluscontrol/homeplusplug.py
homepluscontrol/homeplusremote.py
homepluscontrol-0.1.dist-info/LICENSE
homepluscontrol-0.1.dist-info/METADATA
homepluscontrol-0.1.dist-info/WHEEL
homepluscontrol-0.1.dist-info/top_level.txt
homepluscontrol-0.1.dist-info/RECORD
