Metadata-Version: 2.1
Name: homepluscontrol
Version: 0.1
Summary: Python-based API to interact with the Legrand Home + Control interface
Home-page: https://github.com/chemaaa/homepluscontrol
Author: chemaaa
Author-email: chemaaar@gmail.com
License: GPLv3
Platform: UNKNOWN
Classifier: Programming Language :: Python :: 3
Classifier: License :: OSI Approved :: GNU General Public License v3 (GPLv3)
Classifier: Operating System :: OS Independent
Classifier: Development Status :: 3 - Alpha
Classifier: Framework :: AsyncIO
Classifier: Framework :: Pytest
Classifier: Intended Audience :: Developers
Classifier: Natural Language :: English
Classifier: Topic :: Home Automation
Classifier: Topic :: Software Development :: Libraries :: Python Modules
Requires-Python: >=3.6
License-File: LICENSE
Requires-Dist: aiohttp (>=3.7.1)
Requires-Dist: PyJWT (>=1.7.1)
Requires-Dist: yarl (>=1.4.2)
